{"name":"surf_for_all","lightmapUrl":"https://raw.githubusercontent.com/RSCSurf/SurfMaps2/main/maps/surf_for_all/lightmap.json?v=2048-d214","leafPages":[{"first":0,"count":8040,"url":"https://raw.githubusercontent.com/RSCSurf/SurfMaps2/main/maps/surf_for_all/geom/leafpage0.json?v=2048-d214"}],"dispPages":[{"first":0,"count":0,"url":"https://raw.githubusercontent.com/RSCSurf/SurfMaps2/main/maps/surf_for_all/geom/disppage0.json?v=2048-d214"}],"materialPages":[{"first":0,"count":25,"url":"https://raw.githubusercontent.com/RSCSurf/SurfMaps2/main/maps/surf_for_all/materials/matpage0.json?v=2048-d214"}],"brushModelPages":[{"first":0,"count":1,"url":"https://raw.githubusercontent.com/RSCSurf/SurfMaps2/main/maps/surf_for_all/geom/bsppage0.json?v=2048-d214"},{"first":1,"count":54,"url":"https://raw.githubusercontent.com/RSCSurf/SurfMaps2/main/maps/surf_for_all/geom/bsppage1.json?v=2048-d214"}],"studioModelPages":[{"first":0,"count":0,"url":"https://raw.githubusercontent.com/RSCSurf/SurfMaps2/main/maps/surf_for_all/geom/mdlpage0.json?v=2048-d214"}],"vertLightingPages":[{"first":0,"count":0,"url":"https://raw.githubusercontent.com/RSCSurf/SurfMaps2/main/maps/surf_for_all/geom/vhvpage0.json?v=2048-d214"}],"visPages":[{"first":0,"count":3645,"url":"https://raw.githubusercontent.com/RSCSurf/SurfMaps2/main/maps/surf_for_all/geom/vispage0.json?v=2048-d214"}],"ambientPages":[{"first":0,"count":4096,"url":"https://raw.githubusercontent.com/RSCSurf/SurfMaps2/main/maps/surf_for_all/geom/ambientpage0.json?v=2048-d214"},{"first":4096,"count":3944,"url":"https://raw.githubusercontent.com/RSCSurf/SurfMaps2/main/maps/surf_for_all/geom/ambientpage1.json?v=2048-d214"}],"entities":[{"skyMaterial":{"shader":"SourceUtils.Shaders.Sky","properties":[{"name":"cullFace","type":1,"value":false},{"name":"facePosX","type":4,"value":"https://raw.githubusercontent.com/RSCSurf/SurfMaps2/main/maps/surf_for_all/materials/skybox/sky56rt.vtf.json?v=2048-d214"},{"name":"faceNegX","type":4,"value":"https://raw.githubusercontent.com/RSCSurf/SurfMaps2/main/maps/surf_for_all/materials/skybox/sky56lf.vtf.json?v=2048-d214"},{"name":"facePosY","type":4,"value":"https://raw.githubusercontent.com/RSCSurf/SurfMaps2/main/maps/surf_for_all/materials/skybox/sky56bk.vtf.json?v=2048-d214"},{"name":"faceNegY","type":4,"value":"https://raw.githubusercontent.com/RSCSurf/SurfMaps2/main/maps/surf_for_all/materials/skybox/sky56ft.vtf.json?v=2048-d214"},{"name":"facePosZ","type":4,"value":"https://raw.githubusercontent.com/RSCSurf/SurfMaps2/main/maps/surf_for_all/materials/skybox/sky56up.vtf.json?v=2048-d214"},{"name":"faceNegZ","type":4,"value":"https://raw.githubusercontent.com/RSCSurf/SurfMaps2/main/maps/surf_for_all/materials/skybox/sky56dn.vtf.json?v=2048-d214"}]},"model":0,"classname":"worldspawn"},{"classname":"light","origin":{"x":-961.75,"y":3387.3,"z":-108.927}},{"classname":"light","origin":{"x":-961.75,"y":2578.08,"z":-108.927}},{"classname":"light","origin":{"x":702.25,"y":3387.3,"z":-492.927}},{"classname":"light","origin":{"x":702.25,"y":2578.08,"z":-492.927}},{"classname":"light","origin":{"x":2174.25,"y":3387.3,"z":147.073}},{"classname":"light","origin":{"x":2174.25,"y":2578.08,"z":147.073}},{"classname":"light","origin":{"x":3262.25,"y":3387.3,"z":-492.927}},{"classname":"light","origin":{"x":3262.25,"y":2578.08,"z":-492.927}},{"classname":"light","origin":{"x":4030.25,"y":3401.08,"z":-3180.93}},{"classname":"light","origin":{"x":4030.25,"y":2582.92,"z":-3180.93}},{"classname":"light","origin":{"x":1398.25,"y":2582.92,"z":-3116.93}},{"classname":"light","origin":{"x":1398.25,"y":3401.08,"z":-3116.93}},{"classname":"light","origin":{"x":-817.75,"y":2582.92,"z":-3052.93}},{"classname":"light","origin":{"x":-817.75,"y":3401.08,"z":-3052.93}},{"classname":"light","origin":{"x":-2337.75,"y":2134.92,"z":-3036.93}},{"classname":"light","origin":{"x":-2337.75,"y":3849.08,"z":-3036.93}},{"classname":"light","origin":{"x":-1369.75,"y":3849.08,"z":-4330.13}},{"classname":"light","origin":{"x":-1369.75,"y":2134.92,"z":-4330.13}},{"classname":"light","origin":{"x":1182.25,"y":3849.08,"z":-4330.13}},{"classname":"light","origin":{"x":1182.25,"y":2134.92,"z":-4330.13}},{"classname":"light","origin":{"x":3278.25,"y":3849.08,"z":-4330.13}},{"classname":"light","origin":{"x":3278.25,"y":2134.92,"z":-4330.13}},{"classname":"light","origin":{"x":-2337.75,"y":3849.08,"z":-4330.13}},{"classname":"light","origin":{"x":-2337.75,"y":2134.92,"z":-4330.13}},{"classname":"light","origin":{"x":-6252.92,"y":-7848.25,"z":4596.87}},{"classname":"light","origin":{"x":-7692.08,"y":-7848.25,"z":4596.87}},{"classname":"light","origin":{"x":-1797.08,"y":-7848.25,"z":-1407.13}},{"classname":"light","origin":{"x":509.076,"y":-7848.25,"z":-1407.13}},{"classname":"light","origin":{"x":-3309.0,"y":-8944.0,"z":1058.0}},{"classname":"light","origin":{"x":-3309.0,"y":-8376.0,"z":1054.0}},{"classname":"light","origin":{"x":-3309.0,"y":-7744.0,"z":1066.0}},{"classname":"light","origin":{"x":-3309.0,"y":-7288.0,"z":1054.0}},{"classname":"light","origin":{"x":-3309.0,"y":-6832.04,"z":1061.97}},{"classname":"light","origin":{"x":1171.0,"y":-8944.0,"z":-6078.0}},{"classname":"light","origin":{"x":1171.0,"y":-8376.0,"z":-6082.0}},{"classname":"light","origin":{"x":1171.0,"y":-7744.0,"z":-6070.0}},{"classname":"light","origin":{"x":1171.0,"y":-7288.0,"z":-6082.0}},{"classname":"light","origin":{"x":1171.0,"y":-6832.04,"z":-6074.03}},{"classname":"light","origin":{"x":-2491.0,"y":-8944.0,"z":-6078.0}},{"classname":"light","origin":{"x":-2491.0,"y":-8376.0,"z":-6082.0}},{"classname":"light","origin":{"x":-2491.0,"y":-7744.0,"z":-6070.0}},{"classname":"light","origin":{"x":-2491.0,"y":-7288.0,"z":-6082.0}},{"classname":"light","origin":{"x":-2491.0,"y":-6832.04,"z":-6074.03}},{"classname":"light","origin":{"x":378.251,"y":-5960.92,"z":-6079.13}},{"classname":"light","origin":{"x":-1669.75,"y":-5960.92,"z":-6079.13}},{"classname":"light","origin":{"x":-1669.75,"y":-9675.08,"z":-6079.13}},{"classname":"light","origin":{"x":378.251,"y":-9675.08,"z":-6079.13}},{"classname":"light","origin":{"x":-645.75,"y":-5384.92,"z":-7519.13}},{"classname":"light","origin":{"x":-645.75,"y":-10311.9,"z":-7519.13}},{"classname":"light","origin":{"x":4363.0,"y":6556.0,"z":7616.51}},{"classname":"light","origin":{"x":5755.0,"y":6556.0,"z":7616.51}},{"classname":"light","origin":{"x":5059.0,"y":6116.0,"z":7616.51}},{"classname":"light","origin":{"x":5443.0,"y":6996.0,"z":7616.51}},{"classname":"light","origin":{"x":4675.0,"y":6996.0,"z":7616.51}},{"classname":"light","origin":{"x":4363.0,"y":7516.0,"z":6176.51}},{"classname":"light","origin":{"x":4363.0,"y":8028.0,"z":6176.51}},{"classname":"light","origin":{"x":5755.0,"y":8028.0,"z":6176.51}},{"classname":"light","origin":{"x":5755.0,"y":7516.0,"z":6176.51}},{"classname":"light","origin":{"x":4803.0,"y":8532.0,"z":6176.51}},{"classname":"light","origin":{"x":5315.0,"y":8532.0,"z":6176.51}},{"classname":"light","origin":{"x":4363.0,"y":8028.0,"z":5344.51}},{"classname":"light","origin":{"x":4363.0,"y":7516.0,"z":5344.51}},{"classname":"light","origin":{"x":5755.0,"y":8028.0,"z":5344.51}},{"classname":"light","origin":{"x":5755.0,"y":7516.0,"z":5344.51}},{"classname":"light","origin":{"x":5055.0,"y":2276.0,"z":3808.51}},{"classname":"light","origin":{"x":5411.0,"y":2276.0,"z":3808.51}},{"classname":"light","origin":{"x":4707.0,"y":2276.0,"z":3808.51}},{"classname":"light","origin":{"x":4707.0,"y":2276.0,"z":3296.51}},{"classname":"light","origin":{"x":5055.0,"y":2276.0,"z":3296.51}},{"classname":"light","origin":{"x":5411.0,"y":2276.0,"z":3296.51}},{"classname":"light","origin":{"x":8251.0,"y":10652.0,"z":7616.51}},{"classname":"light","origin":{"x":6347.0,"y":10652.0,"z":7616.51}},{"classname":"light","origin":{"x":7323.0,"y":11092.0,"z":7616.51}},{"classname":"light","origin":{"x":6787.0,"y":4076.0,"z":6592.0}},{"classname":"light","origin":{"x":7043.0,"y":4076.0,"z":6592.0}},{"classname":"light","origin":{"x":7299.0,"y":4076.0,"z":6592.0}},{"classname":"light","origin":{"x":7555.0,"y":4076.0,"z":6592.0}},{"classname":"light","origin":{"x":7811.0,"y":4076.0,"z":6592.0}},{"classname":"light","origin":{"x":6595.0,"y":9940.0,"z":7232.51}},{"classname":"light","origin":{"x":8003.0,"y":9940.0,"z":7232.51}},{"classname":"light","origin":{"x":8003.0,"y":9940.0,"z":6064.51}},{"classname":"light","origin":{"x":6595.0,"y":9940.0,"z":6064.51}},{"classname":"light","origin":{"x":6347.0,"y":7484.0,"z":5408.51}},{"classname":"light","origin":{"x":8251.0,"y":7484.0,"z":5408.51}},{"classname":"light","origin":{"x":8251.0,"y":6556.0,"z":5408.51}},{"classname":"light","origin":{"x":6347.0,"y":6556.0,"z":5408.51}},{"classname":"light","origin":{"x":8251.0,"y":5788.0,"z":5408.51}},{"classname":"light","origin":{"x":6347.0,"y":5788.0,"z":5408.51}},{"classname":"light","origin":{"x":8251.0,"y":5020.0,"z":5408.51}},{"classname":"light","origin":{"x":6347.0,"y":5020.0,"z":5408.51}},{"classname":"light","origin":{"x":8251.0,"y":4252.0,"z":5408.51}},{"classname":"light","origin":{"x":6347.0,"y":4252.0,"z":5408.51}},{"classname":"light","origin":{"x":8251.0,"y":2460.0,"z":5408.51}},{"classname":"light","origin":{"x":6347.0,"y":2460.0,"z":5408.51}},{"classname":"light","origin":{"x":8251.0,"y":1692.0,"z":5408.51}},{"classname":"light","origin":{"x":6347.0,"y":1692.0,"z":5408.51}},{"classname":"light","origin":{"x":8251.0,"y":924.0,"z":5408.51}},{"classname":"light","origin":{"x":6347.0,"y":924.0,"z":5408.51}},{"classname":"light","origin":{"x":8251.0,"y":156.0,"z":5408.51}},{"classname":"light","origin":{"x":6347.0,"y":156.0,"z":5408.51}},{"classname":"light","origin":{"x":7771.0,"y":-1188.0,"z":5568.51}},{"classname":"light","origin":{"x":6955.0,"y":-1188.0,"z":5568.51}},{"classname":"light","origin":{"x":7363.0,"y":-1468.0,"z":5568.51}},{"classname":"light","origin":{"x":7771.0,"y":-1188.0,"z":3456.51}},{"classname":"light","origin":{"x":6955.0,"y":-1188.0,"z":3456.51}},{"classname":"light","origin":{"x":7363.0,"y":-1468.0,"z":3456.51}},{"classname":"light","origin":{"x":7771.0,"y":-420.0,"z":3424.51}},{"classname":"light","origin":{"x":6955.0,"y":-420.0,"z":3424.51}},{"classname":"light","origin":{"x":7771.0,"y":252.0,"z":3424.51}},{"classname":"light","origin":{"x":6955.0,"y":252.0,"z":3424.51}},{"classname":"light","origin":{"x":6347.0,"y":3436.0,"z":5312.51}},{"classname":"light","origin":{"x":8251.0,"y":3436.0,"z":5312.51}},{"classname":"info_player_counterterrorist","origin":{"x":1080.0,"y":6656.0,"z":7776.0},"angles":{"x":0.0,"y":270.0,"z":0.0}},{"classname":"info_player_counterterrorist","origin":{"x":1008.0,"y":6656.0,"z":7776.0},"angles":{"x":0.0,"y":270.0,"z":0.0}},{"classname":"info_player_counterterrorist","origin":{"x":936.0,"y":6656.0,"z":7776.0},"angles":{"x":0.0,"y":270.0,"z":0.0}},{"classname":"info_player_counterterrorist","origin":{"x":864.0,"y":6656.0,"z":7776.0},"angles":{"x":0.0,"y":270.0,"z":0.0}},{"classname":"info_player_counterterrorist","origin":{"x":784.0,"y":6656.0,"z":7776.0},"angles":{"x":0.0,"y":270.0,"z":0.0}},{"classname":"info_player_counterterrorist","origin":{"x":1080.0,"y":6696.0,"z":7776.0},"angles":{"x":0.0,"y":270.0,"z":0.0}},{"classname":"info_player_counterterrorist","origin":{"x":1008.0,"y":6696.0,"z":7776.0},"angles":{"x":0.0,"y":270.0,"z":0.0}},{"classname":"info_player_counterterrorist","origin":{"x":936.0,"y":6696.0,"z":7776.0},"angles":{"x":0.0,"y":270.0,"z":0.0}},{"classname":"info_player_counterterrorist","origin":{"x":864.0,"y":6696.0,"z":7776.0},"angles":{"x":0.0,"y":270.0,"z":0.0}},{"classname":"info_player_counterterrorist","origin":{"x":784.0,"y":6696.0,"z":7776.0},"angles":{"x":0.0,"y":270.0,"z":0.0}},{"classname":"info_player_counterterrorist","origin":{"x":1080.0,"y":6728.0,"z":7776.0},"angles":{"x":0.0,"y":270.0,"z":0.0}},{"classname":"info_player_counterterrorist","origin":{"x":1008.0,"y":6728.0,"z":7776.0},"angles":{"x":0.0,"y":270.0,"z":0.0}},{"classname":"info_player_counterterrorist","origin":{"x":936.0,"y":6728.0,"z":7776.0},"angles":{"x":0.0,"y":270.0,"z":0.0}},{"classname":"info_player_counterterrorist","origin":{"x":864.0,"y":6728.0,"z":7776.0},"angles":{"x":0.0,"y":270.0,"z":0.0}},{"classname":"info_player_counterterrorist","origin":{"x":784.0,"y":6728.0,"z":7776.0},"angles":{"x":0.0,"y":270.0,"z":0.0}},{"classname":"info_player_counterterrorist","origin":{"x":1080.0,"y":6768.0,"z":7776.0},"angles":{"x":0.0,"y":270.0,"z":0.0}},{"classname":"info_player_counterterrorist","origin":{"x":1008.0,"y":6768.0,"z":7776.0},"angles":{"x":0.0,"y":270.0,"z":0.0}},{"classname":"info_player_counterterrorist","origin":{"x":936.0,"y":6768.0,"z":7776.0},"angles":{"x":0.0,"y":270.0,"z":0.0}},{"classname":"info_player_counterterrorist","origin":{"x":864.0,"y":6768.0,"z":7776.0},"angles":{"x":0.0,"y":270.0,"z":0.0}},{"classname":"info_player_counterterrorist","origin":{"x":784.0,"y":6768.0,"z":7776.0},"angles":{"x":0.0,"y":270.0,"z":0.0}},{"classname":"info_player_counterterrorist","origin":{"x":1080.0,"y":6808.0,"z":7776.0},"angles":{"x":0.0,"y":270.0,"z":0.0}},{"classname":"info_player_counterterrorist","origin":{"x":1008.0,"y":6808.0,"z":7776.0},"angles":{"x":0.0,"y":270.0,"z":0.0}},{"classname":"info_player_counterterrorist","origin":{"x":936.0,"y":6808.0,"z":7776.0},"angles":{"x":0.0,"y":270.0,"z":0.0}},{"classname":"info_player_counterterrorist","origin":{"x":864.0,"y":6808.0,"z":7776.0},"angles":{"x":0.0,"y":270.0,"z":0.0}},{"classname":"info_player_counterterrorist","origin":{"x":784.0,"y":6808.0,"z":7776.0},"angles":{"x":0.0,"y":270.0,"z":0.0}},{"classname":"info_player_counterterrorist","origin":{"x":1080.0,"y":6848.0,"z":7776.0},"angles":{"x":0.0,"y":270.0,"z":0.0}},{"classname":"info_player_counterterrorist","origin":{"x":1008.0,"y":6848.0,"z":7776.0},"angles":{"x":0.0,"y":270.0,"z":0.0}},{"classname":"info_player_counterterrorist","origin":{"x":936.0,"y":6848.0,"z":7776.0},"angles":{"x":0.0,"y":270.0,"z":0.0}},{"classname":"info_player_counterterrorist","origin":{"x":864.0,"y":6848.0,"z":7776.0},"angles":{"x":0.0,"y":270.0,"z":0.0}},{"classname":"info_player_counterterrorist","origin":{"x":784.0,"y":6848.0,"z":7776.0},"angles":{"x":0.0,"y":270.0,"z":0.0}},{"classname":"info_player_counterterrorist","origin":{"x":1080.0,"y":6880.0,"z":7776.0},"angles":{"x":0.0,"y":270.0,"z":0.0}},{"classname":"info_player_counterterrorist","origin":{"x":1008.0,"y":6880.0,"z":7776.0},"angles":{"x":0.0,"y":270.0,"z":0.0}},{"classname":"info_player_counterterrorist","origin":{"x":936.0,"y":6880.0,"z":7776.0},"angles":{"x":0.0,"y":270.0,"z":0.0}},{"classname":"info_player_counterterrorist","origin":{"x":864.0,"y":6880.0,"z":7776.0},"angles":{"x":0.0,"y":270.0,"z":0.0}},{"classname":"info_player_counterterrorist","origin":{"x":784.0,"y":6880.0,"z":7776.0},"angles":{"x":0.0,"y":270.0,"z":0.0}},{"classname":"info_player_counterterrorist","origin":{"x":1080.0,"y":6920.0,"z":7776.0},"angles":{"x":0.0,"y":270.0,"z":0.0}},{"classname":"info_player_counterterrorist","origin":{"x":1008.0,"y":6920.0,"z":7776.0},"angles":{"x":0.0,"y":270.0,"z":0.0}},{"classname":"info_player_counterterrorist","origin":{"x":936.0,"y":6920.0,"z":7776.0},"angles":{"x":0.0,"y":270.0,"z":0.0}},{"classname":"info_player_counterterrorist","origin":{"x":864.0,"y":6920.0,"z":7776.0},"angles":{"x":0.0,"y":270.0,"z":0.0}},{"classname":"info_player_counterterrorist","origin":{"x":784.0,"y":6920.0,"z":7776.0},"angles":{"x":0.0,"y":270.0,"z":0.0}},{"classname":"info_player_terrorist","origin":{"x":240.0,"y":6656.0,"z":7776.0},"angles":{"x":0.0,"y":270.0,"z":0.0}},{"classname":"info_player_terrorist","origin":{"x":168.0,"y":6656.0,"z":7776.0},"angles":{"x":0.0,"y":270.0,"z":0.0}},{"classname":"info_player_terrorist","origin":{"x":96.0,"y":6656.0,"z":7776.0},"angles":{"x":0.0,"y":270.0,"z":0.0}},{"classname":"info_player_terrorist","origin":{"x":24.0,"y":6656.0,"z":7776.0},"angles":{"x":0.0,"y":270.0,"z":0.0}},{"classname":"info_player_terrorist","origin":{"x":-56.0,"y":6656.0,"z":7776.0},"angles":{"x":0.0,"y":270.0,"z":0.0}},{"classname":"info_player_terrorist","origin":{"x":240.0,"y":6696.0,"z":7776.0},"angles":{"x":0.0,"y":270.0,"z":0.0}},{"classname":"info_player_terrorist","origin":{"x":168.0,"y":6696.0,"z":7776.0},"angles":{"x":0.0,"y":270.0,"z":0.0}},{"classname":"info_player_terrorist","origin":{"x":96.0,"y":6696.0,"z":7776.0},"angles":{"x":0.0,"y":270.0,"z":0.0}},{"classname":"info_player_terrorist","origin":{"x":24.0,"y":6696.0,"z":7776.0},"angles":{"x":0.0,"y":270.0,"z":0.0}},{"classname":"info_player_terrorist","origin":{"x":-56.0,"y":6696.0,"z":7776.0},"angles":{"x":0.0,"y":270.0,"z":0.0}},{"classname":"info_player_terrorist","origin":{"x":240.0,"y":6728.0,"z":7776.0},"angles":{"x":0.0,"y":270.0,"z":0.0}},{"classname":"info_player_terrorist","origin":{"x":168.0,"y":6728.0,"z":7776.0},"angles":{"x":0.0,"y":270.0,"z":0.0}},{"classname":"info_player_terrorist","origin":{"x":96.0,"y":6728.0,"z":7776.0},"angles":{"x":0.0,"y":270.0,"z":0.0}},{"classname":"info_player_terrorist","origin":{"x":24.0,"y":6728.0,"z":7776.0},"angles":{"x":0.0,"y":270.0,"z":0.0}},{"classname":"info_player_terrorist","origin":{"x":-56.0,"y":6728.0,"z":7776.0},"angles":{"x":0.0,"y":270.0,"z":0.0}},{"classname":"info_player_terrorist","origin":{"x":240.0,"y":6768.0,"z":7776.0},"angles":{"x":0.0,"y":270.0,"z":0.0}},{"classname":"info_player_terrorist","origin":{"x":168.0,"y":6768.0,"z":7776.0},"angles":{"x":0.0,"y":270.0,"z":0.0}},{"classname":"info_player_terrorist","origin":{"x":96.0,"y":6768.0,"z":7776.0},"angles":{"x":0.0,"y":270.0,"z":0.0}},{"classname":"info_player_terrorist","origin":{"x":24.0,"y":6768.0,"z":7776.0},"angles":{"x":0.0,"y":270.0,"z":0.0}},{"classname":"info_player_terrorist","origin":{"x":-56.0,"y":6768.0,"z":7776.0},"angles":{"x":0.0,"y":270.0,"z":0.0}},{"classname":"info_player_terrorist","origin":{"x":240.0,"y":6808.0,"z":7776.0},"angles":{"x":0.0,"y":270.0,"z":0.0}},{"classname":"info_player_terrorist","origin":{"x":168.0,"y":6808.0,"z":7776.0},"angles":{"x":0.0,"y":270.0,"z":0.0}},{"classname":"info_player_terrorist","origin":{"x":96.0,"y":6808.0,"z":7776.0},"angles":{"x":0.0,"y":270.0,"z":0.0}},{"classname":"info_player_terrorist","origin":{"x":24.0,"y":6808.0,"z":7776.0},"angles":{"x":0.0,"y":270.0,"z":0.0}},{"classname":"info_player_terrorist","origin":{"x":-56.0,"y":6808.0,"z":7776.0},"angles":{"x":0.0,"y":270.0,"z":0.0}},{"classname":"info_player_terrorist","origin":{"x":240.0,"y":6848.0,"z":7776.0},"angles":{"x":0.0,"y":270.0,"z":0.0}},{"classname":"info_player_terrorist","origin":{"x":168.0,"y":6848.0,"z":7776.0},"angles":{"x":0.0,"y":270.0,"z":0.0}},{"classname":"info_player_terrorist","origin":{"x":96.0,"y":6848.0,"z":7776.0},"angles":{"x":0.0,"y":270.0,"z":0.0}},{"classname":"info_player_terrorist","origin":{"x":24.0,"y":6848.0,"z":7776.0},"angles":{"x":0.0,"y":270.0,"z":0.0}},{"classname":"info_player_terrorist","origin":{"x":-56.0,"y":6848.0,"z":7776.0},"angles":{"x":0.0,"y":270.0,"z":0.0}},{"classname":"info_player_terrorist","origin":{"x":240.0,"y":6880.0,"z":7776.0},"angles":{"x":0.0,"y":270.0,"z":0.0}},{"classname":"info_player_terrorist","origin":{"x":168.0,"y":6880.0,"z":7776.0},"angles":{"x":0.0,"y":270.0,"z":0.0}},{"classname":"info_player_terrorist","origin":{"x":96.0,"y":6880.0,"z":7776.0},"angles":{"x":0.0,"y":270.0,"z":0.0}},{"classname":"info_player_terrorist","origin":{"x":24.0,"y":6880.0,"z":7776.0},"angles":{"x":0.0,"y":270.0,"z":0.0}},{"classname":"info_player_terrorist","origin":{"x":-56.0,"y":6880.0,"z":7776.0},"angles":{"x":0.0,"y":270.0,"z":0.0}},{"classname":"info_player_terrorist","origin":{"x":240.0,"y":6920.0,"z":7776.0},"angles":{"x":0.0,"y":270.0,"z":0.0}},{"classname":"info_player_terrorist","origin":{"x":168.0,"y":6920.0,"z":7776.0},"angles":{"x":0.0,"y":270.0,"z":0.0}},{"classname":"info_player_terrorist","origin":{"x":96.0,"y":6920.0,"z":7776.0},"angles":{"x":0.0,"y":270.0,"z":0.0}},{"classname":"info_player_terrorist","origin":{"x":24.0,"y":6920.0,"z":7776.0},"angles":{"x":0.0,"y":270.0,"z":0.0}},{"classname":"info_player_terrorist","origin":{"x":-56.0,"y":6920.0,"z":7776.0},"angles":{"x":0.0,"y":270.0,"z":0.0}},{"classname":"light","origin":{"x":0.0,"y":-6.67233,"z":224.0}},{"classname":"light","origin":{"x":0.0,"y":-6.67233,"z":-512.0}},{"classname":"light","origin":{"x":0.0,"y":-6.67233,"z":-1280.0}},{"classname":"light","origin":{"x":-768.0,"y":-6.67233,"z":-1792.0}},{"classname":"light","origin":{"x":768.0,"y":-6.67233,"z":-1792.0}},{"classname":"light","origin":{"x":0.0,"y":-768.0,"z":-1792.0}},{"classname":"light","origin":{"x":0.0,"y":768.0,"z":-1792.0}},{"classname":"light","origin":{"x":0.0,"y":-6.67233,"z":-2816.0}},{"classname":"light","origin":{"x":0.0,"y":-6.67233,"z":-3584.0}},{"classname":"light","origin":{"x":0.0,"y":-6.67233,"z":-4352.0}},{"targetname":"stage 1","classname":"info_teleport_destination","origin":{"x":-238.068,"y":305.587,"z":73.0},"angles":{"x":0.0,"y":0.0,"z":0.0}},{"classname":"trigger_teleport","origin":{"x":0.0,"y":0.0,"z":-1535.5}},{"classname":"trigger_teleport","origin":{"x":-512.0,"y":0.0,"z":-3135.5}},{"classname":"trigger_teleport","origin":{"x":512.0,"y":0.0,"z":-3135.5}},{"classname":"trigger_teleport","origin":{"x":0.0,"y":-832.0,"z":-3135.5}},{"classname":"trigger_teleport","origin":{"x":0.0,"y":848.0,"z":-3135.5}},{"Brightness":{"R":58,"G":228,"B":190,"A":200},"Ambient":{"R":255,"G":255,"B":255,"A":20},"BrightnessHdr":{"R":255,"G":255,"B":255,"A":1},"AmbientHdr":{"R":255,"G":255,"B":255,"A":1},"BrightnessScaleHdr":1.0,"AmbientScaleHdr":1.0,"Pitch":0.0,"classname":"light_environment","origin":{"x":318.58,"y":-232.558,"z":73.0},"angles":{"x":0.0,"y":0.0,"z":0.0}},{"classname":"water_lod_control","origin":{"x":383.947,"y":-181.392,"z":73.0}},{"classname":"trigger_teleport","origin":{"x":0.0,"y":0.0,"z":-3071.5}},{"targetname":"stage2","classname":"info_teleport_destination","origin":{"x":-960.0,"y":2992.0,"z":760.0},"angles":{"x":0.0,"y":0.0,"z":0.0}},{"classname":"trigger_teleport","origin":{"x":-192.0,"y":2992.0,"z":-1135.5}},{"classname":"trigger_teleport","origin":{"x":1632.0,"y":2992.0,"z":-815.5}},{"classname":"trigger_teleport","origin":{"x":2720.0,"y":2992.0,"z":-815.5}},{"classname":"trigger_teleport","origin":{"x":3008.0,"y":2992.0,"z":-3887.5}},{"classname":"trigger_teleport","origin":{"x":-704.0,"y":2992.0,"z":-3887.5}},{"classname":"trigger_teleport","origin":{"x":1152.0,"y":2992.0,"z":-4143.5}},{"classname":"trigger_teleport","origin":{"x":833.0,"y":2992.0,"z":-4783.5}},{"Brightness":{"R":255,"G":255,"B":255,"A":200},"Ambient":{"R":255,"G":255,"B":255,"A":20},"BrightnessHdr":{"R":255,"G":255,"B":255,"A":1},"AmbientHdr":{"R":255,"G":255,"B":255,"A":1},"BrightnessScaleHdr":1.0,"AmbientScaleHdr":1.0,"Pitch":0.0,"classname":"light_environment","origin":{"x":-876.357,"y":2800.0,"z":608.0},"angles":{"x":0.0,"y":0.0,"z":0.0}},{"classname":"trigger_teleport","origin":{"x":0.0,"y":0.0,"z":-4520.0}},{"classname":"trigger_teleport","origin":{"x":3744.0,"y":2992.0,"z":-1391.5}},{"classname":"trigger_teleport","origin":{"x":3424.0,"y":2992.0,"z":-1903.5}},{"classname":"trigger_teleport","origin":{"x":4064.0,"y":2992.0,"z":-1903.5}},{"targetname":"stage3","classname":"info_teleport_destination","origin":{"x":-7060.0,"y":-7850.0,"z":4787.0},"angles":{"x":0.0,"y":0.0,"z":0.0}},{"classname":"trigger_teleport","origin":{"x":-6020.0,"y":-7850.0,"z":563.5}},{"classname":"trigger_teleport","origin":{"x":-2548.0,"y":-7850.0,"z":52.0}},{"classname":"trigger_teleport","origin":{"x":-628.0,"y":-7850.0,"z":-460.5}},{"classname":"trigger_teleport","origin":{"x":-644.0,"y":-7850.0,"z":-972.0}},{"classname":"trigger_teleport","origin":{"x":-644.0,"y":-7850.0,"z":-3276.5}},{"classname":"trigger_teleport","origin":{"x":-644.0,"y":-7850.0,"z":-3916.5}},{"classname":"trigger_teleport","origin":{"x":-644.0,"y":-7818.0,"z":-5324.5}},{"classname":"trigger_teleport","origin":{"x":-644.0,"y":-7818.0,"z":-6700.5}},{"classname":"trigger_teleport","origin":{"x":-644.0,"y":-7866.0,"z":-8108.5}},{"classname":"trigger_teleport","origin":{"x":-644.0,"y":-7866.0,"z":-8076.5}},{"classname":"trigger_teleport","origin":{"x":-644.0,"y":-4778.0,"z":-6348.0}},{"classname":"trigger_teleport","origin":{"x":-644.0,"y":-10922.0,"z":-6348.0}},{"classname":"trigger_teleport","origin":{"x":-8428.0,"y":-7850.0,"z":2611.5}},{"classname":"trigger_teleport","origin":{"x":-6716.0,"y":-7850.0,"z":3379.5}},{"classname":"light","origin":{"x":-7776.32,"y":-8457.0,"z":2978.85}},{"classname":"light","origin":{"x":-8172.0,"y":-8457.0,"z":2976.0}},{"classname":"light","origin":{"x":-8566.0,"y":-8457.0,"z":2966.0}},{"classname":"light","origin":{"x":-7776.32,"y":-7251.0,"z":2987.85}},{"classname":"light","origin":{"x":-8172.0,"y":-7251.0,"z":2985.0}},{"classname":"light","origin":{"x":-8566.0,"y":-7251.0,"z":2975.0}},{"classname":"light","origin":{"x":-6922.0,"y":-8151.81,"z":1512.0}},{"Brightness":{"R":255,"G":255,"B":255,"A":200},"Ambient":{"R":255,"G":255,"B":255,"A":20},"BrightnessHdr":{"R":255,"G":255,"B":255,"A":1},"AmbientHdr":{"R":255,"G":255,"B":255,"A":1},"BrightnessScaleHdr":1.0,"AmbientScaleHdr":1.0,"Pitch":0.0,"classname":"light_environment","origin":{"x":-7148.65,"y":-7425.71,"z":4252.0},"angles":{"x":0.0,"y":0.0,"z":0.0}},{"classname":"light","origin":{"x":-6922.0,"y":-11387.0,"z":1122.0}},{"classname":"light","origin":{"x":-6922.0,"y":-4300.0,"z":1122.0}},{"classname":"light","origin":{"x":-5236.0,"y":-4317.0,"z":1122.0}},{"classname":"light","origin":{"x":-5236.0,"y":-8168.81,"z":1512.0}},{"classname":"light","origin":{"x":-5236.0,"y":-11404.0,"z":1122.0}},{"classname":"light","origin":{"x":-1092.0,"y":-11498.0,"z":1139.0}},{"classname":"light","origin":{"x":-1092.0,"y":-4138.0,"z":1043.0}},{"classname":"light","origin":{"x":-1092.0,"y":-7818.0,"z":-1453.0}},{"classname":"light","origin":{"x":-6980.0,"y":-7850.0,"z":4595.0}},{"classname":"light","origin":{"x":-8196.0,"y":-7850.0,"z":3475.0}},{"classname":"light","origin":{"x":-1700.0,"y":-7850.0,"z":-4557.0}},{"classname":"light","origin":{"x":412.0,"y":-7850.0,"z":-4557.0}},{"classname":"light","origin":{"x":-644.0,"y":-8906.0,"z":-4621.0}},{"classname":"light","origin":{"x":-644.0,"y":-6794.0,"z":-4621.0}},{"classname":"light","origin":{"x":-644.0,"y":-7850.0,"z":-5581.0}},{"classname":"light","origin":{"x":-1732.0,"y":-7850.0,"z":-6125.0}},{"classname":"light","origin":{"x":604.0,"y":-7850.0,"z":-6157.0}},{"classname":"light","origin":{"x":-1476.0,"y":-7850.0,"z":-7245.0}},{"classname":"light","origin":{"x":156.0,"y":-7850.0,"z":-7245.0}},{"classname":"water_lod_control","origin":{"x":-7076.0,"y":-7887.25,"z":4275.0}},{"classname":"trigger_teleport","origin":{"x":4032.0,"y":2992.0,"z":-4399.5}},{"targetname":"stage4","classname":"info_teleport_destination","origin":{"x":5059.0,"y":6364.0,"z":7704.0},"angles":{"x":0.0,"y":270.0,"z":0.0}},{"classname":"trigger_teleport","origin":{"x":5059.0,"y":7580.0,"z":5888.5}},{"classname":"trigger_teleport","origin":{"x":5059.0,"y":7836.0,"z":5120.5}},{"classname":"trigger_teleport","origin":{"x":5059.0,"y":4636.0,"z":2560.5}},{"classname":"light","origin":{"x":4387.0,"y":5692.0,"z":4016.0}},{"classname":"light","origin":{"x":4387.0,"y":5436.0,"z":4016.0}},{"classname":"light","origin":{"x":4387.0,"y":5180.0,"z":4016.0}},{"classname":"light","origin":{"x":4387.0,"y":4924.0,"z":4016.0}},{"classname":"light","origin":{"x":4387.0,"y":4668.0,"z":4016.0}},{"classname":"light","origin":{"x":4387.0,"y":4412.0,"z":4016.0}},{"classname":"light","origin":{"x":4387.0,"y":4156.0,"z":4016.0}},{"classname":"light","origin":{"x":4387.0,"y":3644.0,"z":4016.0}},{"classname":"light","origin":{"x":4387.0,"y":3900.0,"z":4016.0}},{"classname":"light","origin":{"x":5731.0,"y":5692.0,"z":4016.0}},{"classname":"light","origin":{"x":5731.0,"y":5436.0,"z":4016.0}},{"classname":"light","origin":{"x":5731.0,"y":5180.0,"z":4016.0}},{"classname":"light","origin":{"x":5731.0,"y":4924.0,"z":4016.0}},{"classname":"light","origin":{"x":5731.0,"y":4668.0,"z":4016.0}},{"classname":"light","origin":{"x":5731.0,"y":4412.0,"z":4016.0}},{"classname":"light","origin":{"x":5731.0,"y":4156.0,"z":4016.0}},{"classname":"light","origin":{"x":5731.0,"y":3644.0,"z":4016.0}},{"classname":"light","origin":{"x":5731.0,"y":3900.0,"z":4016.0}},{"classname":"light","origin":{"x":5059.0,"y":4924.0,"z":4016.0}},{"classname":"light","origin":{"x":5059.0,"y":6364.0,"z":7784.0}},{"targetname":"stage5","classname":"info_teleport_destination","origin":{"x":7283.0,"y":10428.0,"z":7904.0},"angles":{"x":0.0,"y":270.0,"z":0.0}},{"classname":"trigger_teleport","origin":{"x":5051.0,"y":2212.0,"z":3608.0}},{"classname":"trigger_teleport","origin":{"x":7299.0,"y":8764.0,"z":4864.5}},{"classname":"trigger_teleport","origin":{"x":7299.0,"y":5724.0,"z":3840.5}},{"classname":"trigger_teleport","origin":{"x":7299.0,"y":3388.0,"z":4800.5}},{"classname":"trigger_teleport","origin":{"x":7299.0,"y":1068.0,"z":3840.5}},{"classname":"trigger_teleport","origin":{"x":7363.0,"y":110.0,"z":3168.5}},{"classname":"trigger_teleport","origin":{"x":7363.0,"y":-1188.0,"z":5248.5}},{"classname":"light","origin":{"x":7363.0,"y":-1092.0,"z":5312.0}},{"classname":"light","origin":{"x":7363.0,"y":-1092.0,"z":3808.0}},{"classname":"light","origin":{"x":7283.0,"y":10437.0,"z":8016.0}},{"classname":"light","origin":{"x":7299.0,"y":10652.0,"z":7616.0}},{"classname":"trigger_push","origin":{"x":-8040.0,"y":-7856.0,"z":1102.0}},{"targetname":"dmgfilter","classname":"filter_damage_type","origin":{"x":558.0,"y":7005.32,"z":7771.8}},{"classname":"game_player_equip","origin":{"x":590.0,"y":6920.0,"z":7768.3}},{"classname":"trigger_multiple","origin":{"x":512.01,"y":6848.0,"z":7760.0}},{"classname":"light","origin":{"x":512.0,"y":6400.0,"z":8000.0}},{"classname":"light","origin":{"x":512.0,"y":6848.0,"z":8000.0}},{"classname":"light","origin":{"x":512.0,"y":6272.0,"z":7424.0}},{"classname":"light","origin":{"x":96.0,"y":6432.0,"z":8000.0}},{"classname":"light","origin":{"x":-64.0,"y":6880.0,"z":8000.0}},{"classname":"light","origin":{"x":960.0,"y":6400.0,"z":8000.0}},{"classname":"light","origin":{"x":1088.0,"y":6848.0,"z":8000.0}},{"classname":"light","origin":{"x":512.0,"y":5888.0,"z":8000.0}},{"classname":"light","origin":{"x":512.0,"y":5920.0,"z":8000.0}},{"classname":"trigger_teleport","origin":{"x":512.0,"y":6272.0,"z":7264.0}},{"classname":"light","origin":{"x":96.0,"y":6432.0,"z":7904.0}},{"classname":"light","origin":{"x":-64.0,"y":6880.0,"z":7904.0}},{"classname":"light","origin":{"x":512.0,"y":6848.0,"z":7904.0}},{"classname":"light","origin":{"x":512.0,"y":6400.0,"z":7904.0}},{"classname":"light","origin":{"x":512.0,"y":5920.0,"z":7904.0}},{"classname":"light","origin":{"x":512.0,"y":5888.0,"z":7904.0}},{"classname":"light","origin":{"x":960.0,"y":6400.0,"z":7904.0}},{"classname":"light","origin":{"x":1088.0,"y":6848.0,"z":7904.0}},{"classname":"light","origin":{"x":96.0,"y":6432.0,"z":8064.0}},{"classname":"light","origin":{"x":-64.0,"y":6880.0,"z":8064.0}},{"classname":"light","origin":{"x":512.0,"y":6848.0,"z":8064.0}},{"classname":"light","origin":{"x":512.0,"y":6400.0,"z":8064.0}},{"classname":"light","origin":{"x":512.0,"y":5920.0,"z":8064.0}},{"classname":"light","origin":{"x":512.0,"y":5888.0,"z":8064.0}},{"classname":"light","origin":{"x":960.0,"y":6400.0,"z":8064.0}},{"classname":"light","origin":{"x":1088.0,"y":6848.0,"z":8064.0}},{"classname":"light","origin":{"x":96.0,"y":6432.0,"z":8160.0}},{"classname":"light","origin":{"x":-64.0,"y":6880.0,"z":8160.0}},{"classname":"light","origin":{"x":512.0,"y":6848.0,"z":8160.0}},{"classname":"light","origin":{"x":512.0,"y":6400.0,"z":8160.0}},{"classname":"light","origin":{"x":512.0,"y":5920.0,"z":8160.0}},{"classname":"light","origin":{"x":512.0,"y":5888.0,"z":8160.0}},{"classname":"light","origin":{"x":960.0,"y":6400.0,"z":8160.0}},{"classname":"light","origin":{"x":1088.0,"y":6848.0,"z":8160.0}},{"classname":"trigger_teleport","origin":{"x":1344.0,"y":16.0,"z":-3135.5}},{"classname":"trigger_teleport","origin":{"x":-1344.0,"y":16.0,"z":-3135.5}},{"targetname":"stage1_start","classname":"trigger_multiple","origin":{"x":0.0,"y":0.0,"z":192.0}},{"classname":"trigger_teleport","origin":{"x":-960.0,"y":2992.0,"z":337.5}},{"targetname":"stage2_start","classname":"trigger_multiple","origin":{"x":-952.0,"y":2992.0,"z":701.0}},{"targetname":"stage3_start","classname":"trigger_multiple","origin":{"x":-7292.01,"y":-7855.0,"z":4567.0}},{"targetname":"stage4_start","classname":"trigger_multiple","origin":{"x":5108.0,"y":6544.0,"z":7595.0}},{"targetname":"stage5_start","classname":"trigger_multiple","origin":{"x":7300.0,"y":10588.0,"z":7723.0}},{"classname":"light","origin":{"x":7367.58,"y":8144.0,"z":6944.0}},{"classname":"light","origin":{"x":7367.58,"y":5976.0,"z":6408.0}},{"classname":"light","origin":{"x":7367.58,"y":4800.0,"z":6672.0}},{"classname":"light","origin":{"x":7367.58,"y":4696.0,"z":5240.0}},{"classname":"light","origin":{"x":7367.58,"y":1376.0,"z":5272.0}},{"classname":"light","origin":{"x":6955.0,"y":832.0,"z":3424.51}},{"classname":"light","origin":{"x":7771.0,"y":832.0,"z":3424.51}},{"classname":"light","origin":{"x":6955.0,"y":1440.0,"z":3424.51}},{"classname":"light","origin":{"x":7771.0,"y":1440.0,"z":3424.51}},{"targetname":"stage5_end","classname":"trigger_multiple","origin":{"x":7366.0,"y":1720.0,"z":3648.0}},{"classname":"point_spotlight","origin":{"x":768.0,"y":6399.98,"z":7711.98},"angles":{"x":0.0,"y":270.0,"z":-180.0}},{"classname":"point_spotlight","origin":{"x":704.0,"y":6399.98,"z":7711.98},"angles":{"x":0.0,"y":270.0,"z":-180.0}},{"classname":"point_spotlight","origin":{"x":640.0,"y":6399.98,"z":7711.98},"angles":{"x":0.0,"y":270.0,"z":-180.0}},{"classname":"point_spotlight","origin":{"x":576.0,"y":6399.98,"z":7711.98},"angles":{"x":0.0,"y":270.0,"z":-180.0}},{"classname":"point_spotlight","origin":{"x":512.0,"y":6399.98,"z":7711.98},"angles":{"x":0.0,"y":270.0,"z":-180.0}},{"classname":"point_spotlight","origin":{"x":448.0,"y":6399.98,"z":7711.98},"angles":{"x":0.0,"y":270.0,"z":-180.0}},{"classname":"point_spotlight","origin":{"x":384.0,"y":6399.98,"z":7711.98},"angles":{"x":0.0,"y":270.0,"z":-180.0}},{"classname":"point_spotlight","origin":{"x":320.0,"y":6399.98,"z":7711.98},"angles":{"x":0.0,"y":270.0,"z":-180.0}},{"classname":"point_spotlight","origin":{"x":256.0,"y":6399.98,"z":7711.98},"angles":{"x":0.0,"y":270.0,"z":-180.0}},{"classname":"point_spotlight","origin":{"x":192.0,"y":6336.0,"z":7712.0},"angles":{"x":0.0,"y":0.0,"z":0.0}},{"classname":"point_spotlight","origin":{"x":192.0,"y":6272.0,"z":7712.0},"angles":{"x":0.0,"y":0.0,"z":0.0}},{"classname":"point_spotlight","origin":{"x":192.0,"y":6208.0,"z":7712.0},"angles":{"x":0.0,"y":0.0,"z":0.0}},{"classname":"point_spotlight","origin":{"x":256.0,"y":6144.0,"z":7712.0},"angles":{"x":0.0,"y":90.0,"z":0.0}},{"classname":"point_spotlight","origin":{"x":320.0,"y":6144.0,"z":7712.0},"angles":{"x":0.0,"y":90.0,"z":0.0}},{"classname":"point_spotlight","origin":{"x":384.0,"y":6144.0,"z":7712.0},"angles":{"x":0.0,"y":90.0,"z":0.0}},{"classname":"point_spotlight","origin":{"x":448.0,"y":6144.0,"z":7712.0},"angles":{"x":0.0,"y":90.0,"z":0.0}},{"classname":"point_spotlight","origin":{"x":832.0,"y":6336.0,"z":7712.0},"angles":{"x":0.0,"y":180.0,"z":0.0}},{"classname":"point_spotlight","origin":{"x":832.0,"y":6272.0,"z":7712.0},"angles":{"x":0.0,"y":180.0,"z":0.0}},{"classname":"point_spotlight","origin":{"x":832.0,"y":6208.0,"z":7712.0},"angles":{"x":0.0,"y":180.0,"z":0.0}},{"classname":"point_spotlight","origin":{"x":768.0,"y":6144.0,"z":7712.0},"angles":{"x":0.0,"y":90.0,"z":0.0}},{"classname":"point_spotlight","origin":{"x":704.0,"y":6144.0,"z":7712.0},"angles":{"x":0.0,"y":90.0,"z":0.0}},{"classname":"point_spotlight","origin":{"x":640.0,"y":6144.0,"z":7712.0},"angles":{"x":0.0,"y":90.0,"z":0.0}},{"classname":"point_spotlight","origin":{"x":576.0,"y":6144.0,"z":7712.0},"angles":{"x":0.0,"y":90.0,"z":0.0}},{"classname":"point_spotlight","origin":{"x":512.0,"y":6144.0,"z":7712.0},"angles":{"x":0.0,"y":90.0,"z":0.0}},{"classname":"point_spotlight","origin":{"x":768.0,"y":6399.98,"z":7615.98},"angles":{"x":0.0,"y":270.0,"z":180.0}},{"classname":"point_spotlight","origin":{"x":704.0,"y":6399.98,"z":7615.98},"angles":{"x":0.0,"y":270.0,"z":180.0}},{"classname":"point_spotlight","origin":{"x":640.0,"y":6399.98,"z":7615.98},"angles":{"x":0.0,"y":270.0,"z":180.0}},{"classname":"point_spotlight","origin":{"x":576.0,"y":6399.98,"z":7615.98},"angles":{"x":0.0,"y":270.0,"z":180.0}},{"classname":"point_spotlight","origin":{"x":512.0,"y":6399.98,"z":7615.98},"angles":{"x":0.0,"y":270.0,"z":180.0}},{"classname":"point_spotlight","origin":{"x":448.0,"y":6399.98,"z":7615.98},"angles":{"x":0.0,"y":270.0,"z":180.0}},{"classname":"point_spotlight","origin":{"x":384.0,"y":6399.98,"z":7615.98},"angles":{"x":0.0,"y":270.0,"z":180.0}},{"classname":"point_spotlight","origin":{"x":320.0,"y":6399.98,"z":7615.98},"angles":{"x":0.0,"y":270.0,"z":180.0}},{"classname":"point_spotlight","origin":{"x":256.0,"y":6399.98,"z":7615.98},"angles":{"x":0.0,"y":270.0,"z":180.0}},{"classname":"point_spotlight","origin":{"x":192.0,"y":6336.0,"z":7616.0},"angles":{"x":0.0,"y":0.0,"z":0.0}},{"classname":"point_spotlight","origin":{"x":192.0,"y":6272.0,"z":7616.0},"angles":{"x":0.0,"y":0.0,"z":0.0}},{"classname":"point_spotlight","origin":{"x":192.0,"y":6208.0,"z":7616.0},"angles":{"x":0.0,"y":0.0,"z":0.0}},{"classname":"point_spotlight","origin":{"x":256.0,"y":6144.0,"z":7616.0},"angles":{"x":0.0,"y":90.0,"z":0.0}},{"classname":"point_spotlight","origin":{"x":320.0,"y":6144.0,"z":7616.0},"angles":{"x":0.0,"y":90.0,"z":0.0}},{"classname":"point_spotlight","origin":{"x":384.0,"y":6144.0,"z":7616.0},"angles":{"x":0.0,"y":90.0,"z":0.0}},{"classname":"point_spotlight","origin":{"x":448.0,"y":6144.0,"z":7616.0},"angles":{"x":0.0,"y":90.0,"z":0.0}},{"classname":"point_spotlight","origin":{"x":832.0,"y":6336.0,"z":7616.0},"angles":{"x":0.0,"y":180.0,"z":0.0}},{"classname":"point_spotlight","origin":{"x":832.0,"y":6272.0,"z":7616.0},"angles":{"x":0.0,"y":180.0,"z":0.0}},{"classname":"point_spotlight","origin":{"x":832.0,"y":6208.0,"z":7616.0},"angles":{"x":0.0,"y":180.0,"z":0.0}},{"classname":"point_spotlight","origin":{"x":768.0,"y":6144.0,"z":7616.0},"angles":{"x":0.0,"y":90.0,"z":0.0}},{"classname":"point_spotlight","origin":{"x":704.0,"y":6144.0,"z":7616.0},"angles":{"x":0.0,"y":90.0,"z":0.0}},{"classname":"point_spotlight","origin":{"x":640.0,"y":6144.0,"z":7616.0},"angles":{"x":0.0,"y":90.0,"z":0.0}},{"classname":"point_spotlight","origin":{"x":576.0,"y":6144.0,"z":7616.0},"angles":{"x":0.0,"y":90.0,"z":0.0}},{"classname":"point_spotlight","origin":{"x":512.0,"y":6144.0,"z":7616.0},"angles":{"x":0.0,"y":90.0,"z":0.0}},{"classname":"point_spotlight","origin":{"x":768.0,"y":6399.98,"z":7519.98},"angles":{"x":0.0,"y":270.0,"z":-180.0}},{"classname":"point_spotlight","origin":{"x":704.0,"y":6399.98,"z":7519.98},"angles":{"x":0.0,"y":270.0,"z":-180.0}},{"classname":"point_spotlight","origin":{"x":640.0,"y":6399.98,"z":7519.98},"angles":{"x":0.0,"y":270.0,"z":-180.0}},{"classname":"point_spotlight","origin":{"x":576.0,"y":6399.98,"z":7519.98},"angles":{"x":0.0,"y":270.0,"z":-180.0}},{"classname":"point_spotlight","origin":{"x":512.0,"y":6399.98,"z":7519.98},"angles":{"x":0.0,"y":270.0,"z":-180.0}},{"classname":"point_spotlight","origin":{"x":448.0,"y":6399.98,"z":7519.98},"angles":{"x":0.0,"y":270.0,"z":-180.0}},{"classname":"point_spotlight","origin":{"x":384.0,"y":6399.98,"z":7519.98},"angles":{"x":0.0,"y":270.0,"z":-180.0}},{"classname":"point_spotlight","origin":{"x":320.0,"y":6399.98,"z":7519.98},"angles":{"x":0.0,"y":270.0,"z":-180.0}},{"classname":"point_spotlight","origin":{"x":256.0,"y":6399.98,"z":7519.98},"angles":{"x":0.0,"y":270.0,"z":-180.0}},{"classname":"point_spotlight","origin":{"x":192.0,"y":6336.0,"z":7520.0},"angles":{"x":0.0,"y":0.0,"z":0.0}},{"classname":"point_spotlight","origin":{"x":192.0,"y":6272.0,"z":7520.0},"angles":{"x":0.0,"y":0.0,"z":0.0}},{"classname":"point_spotlight","origin":{"x":192.0,"y":6208.0,"z":7520.0},"angles":{"x":0.0,"y":0.0,"z":0.0}},{"classname":"point_spotlight","origin":{"x":256.0,"y":6144.0,"z":7520.0},"angles":{"x":0.0,"y":90.0,"z":0.0}},{"classname":"point_spotlight","origin":{"x":320.0,"y":6144.0,"z":7520.0},"angles":{"x":0.0,"y":90.0,"z":0.0}},{"classname":"point_spotlight","origin":{"x":384.0,"y":6144.0,"z":7520.0},"angles":{"x":0.0,"y":90.0,"z":0.0}},{"classname":"point_spotlight","origin":{"x":448.0,"y":6144.0,"z":7520.0},"angles":{"x":0.0,"y":90.0,"z":0.0}},{"classname":"point_spotlight","origin":{"x":832.0,"y":6336.0,"z":7520.0},"angles":{"x":0.0,"y":180.0,"z":0.0}},{"classname":"point_spotlight","origin":{"x":832.0,"y":6272.0,"z":7520.0},"angles":{"x":0.0,"y":180.0,"z":0.0}},{"classname":"point_spotlight","origin":{"x":832.0,"y":6208.0,"z":7520.0},"angles":{"x":0.0,"y":180.0,"z":0.0}},{"classname":"point_spotlight","origin":{"x":768.0,"y":6144.0,"z":7520.0},"angles":{"x":0.0,"y":90.0,"z":0.0}},{"classname":"point_spotlight","origin":{"x":704.0,"y":6144.0,"z":7520.0},"angles":{"x":0.0,"y":90.0,"z":0.0}},{"classname":"point_spotlight","origin":{"x":640.0,"y":6144.0,"z":7520.0},"angles":{"x":0.0,"y":90.0,"z":0.0}},{"classname":"point_spotlight","origin":{"x":576.0,"y":6144.0,"z":7520.0},"angles":{"x":0.0,"y":90.0,"z":0.0}},{"classname":"point_spotlight","origin":{"x":512.0,"y":6144.0,"z":7520.0},"angles":{"x":0.0,"y":90.0,"z":0.0}},{"classname":"point_spotlight","origin":{"x":768.0,"y":6399.98,"z":7423.98},"angles":{"x":0.0,"y":270.0,"z":180.0}},{"classname":"point_spotlight","origin":{"x":704.0,"y":6399.98,"z":7423.98},"angles":{"x":0.0,"y":270.0,"z":180.0}},{"classname":"point_spotlight","origin":{"x":640.0,"y":6399.98,"z":7423.98},"angles":{"x":0.0,"y":270.0,"z":180.0}},{"classname":"point_spotlight","origin":{"x":576.0,"y":6399.98,"z":7423.98},"angles":{"x":0.0,"y":270.0,"z":180.0}},{"classname":"point_spotlight","origin":{"x":512.0,"y":6399.98,"z":7423.98},"angles":{"x":0.0,"y":270.0,"z":180.0}},{"classname":"point_spotlight","origin":{"x":448.0,"y":6399.98,"z":7423.98},"angles":{"x":0.0,"y":270.0,"z":180.0}},{"classname":"point_spotlight","origin":{"x":384.0,"y":6399.98,"z":7423.98},"angles":{"x":0.0,"y":270.0,"z":180.0}},{"classname":"point_spotlight","origin":{"x":320.0,"y":6399.98,"z":7423.98},"angles":{"x":0.0,"y":270.0,"z":180.0}},{"classname":"point_spotlight","origin":{"x":256.0,"y":6399.98,"z":7423.98},"angles":{"x":0.0,"y":270.0,"z":180.0}},{"classname":"point_spotlight","origin":{"x":192.0,"y":6336.0,"z":7424.0},"angles":{"x":0.0,"y":0.0,"z":0.0}},{"classname":"point_spotlight","origin":{"x":192.0,"y":6272.0,"z":7424.0},"angles":{"x":0.0,"y":0.0,"z":0.0}},{"classname":"point_spotlight","origin":{"x":192.0,"y":6208.0,"z":7424.0},"angles":{"x":0.0,"y":0.0,"z":0.0}},{"classname":"point_spotlight","origin":{"x":256.0,"y":6144.0,"z":7424.0},"angles":{"x":0.0,"y":90.0,"z":0.0}},{"classname":"point_spotlight","origin":{"x":320.0,"y":6144.0,"z":7424.0},"angles":{"x":0.0,"y":90.0,"z":0.0}},{"classname":"point_spotlight","origin":{"x":384.0,"y":6144.0,"z":7424.0},"angles":{"x":0.0,"y":90.0,"z":0.0}},{"classname":"point_spotlight","origin":{"x":448.0,"y":6144.0,"z":7424.0},"angles":{"x":0.0,"y":90.0,"z":0.0}},{"classname":"point_spotlight","origin":{"x":832.0,"y":6336.0,"z":7424.0},"angles":{"x":0.0,"y":180.0,"z":0.0}},{"classname":"point_spotlight","origin":{"x":832.0,"y":6272.0,"z":7424.0},"angles":{"x":0.0,"y":180.0,"z":0.0}},{"classname":"point_spotlight","origin":{"x":832.0,"y":6208.0,"z":7424.0},"angles":{"x":0.0,"y":180.0,"z":0.0}},{"classname":"point_spotlight","origin":{"x":768.0,"y":6144.0,"z":7424.0},"angles":{"x":0.0,"y":90.0,"z":0.0}},{"classname":"point_spotlight","origin":{"x":704.0,"y":6144.0,"z":7424.0},"angles":{"x":0.0,"y":90.0,"z":0.0}},{"classname":"point_spotlight","origin":{"x":640.0,"y":6144.0,"z":7424.0},"angles":{"x":0.0,"y":90.0,"z":0.0}},{"classname":"point_spotlight","origin":{"x":576.0,"y":6144.0,"z":7424.0},"angles":{"x":0.0,"y":90.0,"z":0.0}},{"classname":"point_spotlight","origin":{"x":512.0,"y":6144.0,"z":7424.0},"angles":{"x":0.0,"y":90.0,"z":0.0}},{"classname":"point_spotlight","origin":{"x":768.0,"y":6399.98,"z":7347.98},"angles":{"x":0.0,"y":270.0,"z":-180.0}},{"classname":"point_spotlight","origin":{"x":704.0,"y":6399.98,"z":7347.98},"angles":{"x":0.0,"y":270.0,"z":-180.0}},{"classname":"point_spotlight","origin":{"x":640.0,"y":6399.98,"z":7347.98},"angles":{"x":0.0,"y":270.0,"z":-180.0}},{"classname":"point_spotlight","origin":{"x":576.0,"y":6399.98,"z":7347.98},"angles":{"x":0.0,"y":270.0,"z":-180.0}},{"classname":"point_spotlight","origin":{"x":512.0,"y":6399.98,"z":7347.98},"angles":{"x":0.0,"y":270.0,"z":-180.0}},{"classname":"point_spotlight","origin":{"x":448.0,"y":6399.98,"z":7347.98},"angles":{"x":0.0,"y":270.0,"z":-180.0}},{"classname":"point_spotlight","origin":{"x":384.0,"y":6399.98,"z":7347.98},"angles":{"x":0.0,"y":270.0,"z":-180.0}},{"classname":"point_spotlight","origin":{"x":320.0,"y":6399.98,"z":7347.98},"angles":{"x":0.0,"y":270.0,"z":-180.0}},{"classname":"point_spotlight","origin":{"x":256.0,"y":6399.98,"z":7347.98},"angles":{"x":0.0,"y":270.0,"z":-180.0}},{"classname":"point_spotlight","origin":{"x":192.0,"y":6336.0,"z":7348.0},"angles":{"x":0.0,"y":0.0,"z":0.0}},{"classname":"point_spotlight","origin":{"x":192.0,"y":6272.0,"z":7348.0},"angles":{"x":0.0,"y":0.0,"z":0.0}},{"classname":"point_spotlight","origin":{"x":192.0,"y":6208.0,"z":7348.0},"angles":{"x":0.0,"y":0.0,"z":0.0}},{"classname":"point_spotlight","origin":{"x":256.0,"y":6144.0,"z":7348.0},"angles":{"x":0.0,"y":90.0,"z":0.0}},{"classname":"point_spotlight","origin":{"x":320.0,"y":6144.0,"z":7348.0},"angles":{"x":0.0,"y":90.0,"z":0.0}},{"classname":"point_spotlight","origin":{"x":384.0,"y":6144.0,"z":7348.0},"angles":{"x":0.0,"y":90.0,"z":0.0}},{"classname":"point_spotlight","origin":{"x":448.0,"y":6144.0,"z":7348.0},"angles":{"x":0.0,"y":90.0,"z":0.0}},{"classname":"point_spotlight","origin":{"x":832.0,"y":6336.0,"z":7348.0},"angles":{"x":0.0,"y":180.0,"z":0.0}},{"classname":"point_spotlight","origin":{"x":832.0,"y":6272.0,"z":7348.0},"angles":{"x":0.0,"y":180.0,"z":0.0}},{"classname":"point_spotlight","origin":{"x":832.0,"y":6208.0,"z":7348.0},"angles":{"x":0.0,"y":180.0,"z":0.0}},{"classname":"point_spotlight","origin":{"x":768.0,"y":6144.0,"z":7348.0},"angles":{"x":0.0,"y":90.0,"z":0.0}},{"classname":"point_spotlight","origin":{"x":704.0,"y":6144.0,"z":7348.0},"angles":{"x":0.0,"y":90.0,"z":0.0}},{"classname":"point_spotlight","origin":{"x":640.0,"y":6144.0,"z":7348.0},"angles":{"x":0.0,"y":90.0,"z":0.0}},{"classname":"point_spotlight","origin":{"x":576.0,"y":6144.0,"z":7348.0},"angles":{"x":0.0,"y":90.0,"z":0.0}},{"classname":"point_spotlight","origin":{"x":512.0,"y":6144.0,"z":7348.0},"angles":{"x":0.0,"y":90.0,"z":0.0}}]}